hnne/__init__.py
hnne/cool_functions.py
hnne/finch_clustering.py
hnne/hierarchical_projection.py
hnne/point_spreading.py
hnne/projector.py
hnne-0.1.10.dist-info/LICENSE.txt
hnne-0.1.10.dist-info/METADATA
hnne-0.1.10.dist-info/WHEEL
hnne-0.1.10.dist-info/top_level.txt
hnne-0.1.10.dist-info/RECORD
