Metadata-Version: 2.1
Name: hnne
Version: 0.1.10
Summary: A fast hierarchical dimensionality reduction algorithm.
Author: Marios Koulakis, Saquib Sarfraz
Author-email: marios.koulakis@gmail.com, saquibsarfraz@gmail.com
Project-URL: Documentation, https://hnne.readthedocs.io/en/latest/
Project-URL: Repository, https://github.com/koulakis/h-nne
Project-URL: Publication, https://arxiv.org/abs/2203.12997
Keywords: dimension dimensionality reduction t-sne umap hierarchical clustering finch
Classifier: Development Status :: 3 - Alpha
Classifier: License :: Free for non-commercial use
Classifier: Operating System :: Unix
Classifier: Operating System :: MacOS
Classifier: Programming Language :: Python :: 3.7
Classifier: Programming Language :: Python :: 3.8
Classifier: Programming Language :: Python :: 3.9
License-File: LICENSE.txt
Requires-Dist: numba >=0.51.2
Requires-Dist: pynndescent
Requires-Dist: scipy
Requires-Dist: numpy >=1.18
Requires-Dist: scikit-learn
Requires-Dist: tqdm
Requires-Dist: typer
Requires-Dist: pandas
Requires-Dist: cython
